pyrunning/__init__.py
pyrunning/pyrunning.py
pyrunning-0.0.13.dist-info/LICENSE
pyrunning-0.0.13.dist-info/METADATA
pyrunning-0.0.13.dist-info/WHEEL
pyrunning-0.0.13.dist-info/top_level.txt
pyrunning-0.0.13.dist-info/RECORD
